jaxopt/__init__.py
jaxopt/base.py
jaxopt/cond.py
jaxopt/implicit_diff.py
jaxopt/isotonic.py
jaxopt/linear_solve.py
jaxopt/loop.py
jaxopt/loss.py
jaxopt/objective.py
jaxopt/perturbations.py
jaxopt/projection.py
jaxopt/prox.py
jaxopt/tree_util.py
jaxopt/version.py
jaxopt/_src/__init__.py
jaxopt/_src/anderson.py
jaxopt/_src/anderson_wrapper.py
jaxopt/_src/armijo_sgd.py
jaxopt/_src/backtracking_linesearch.py
jaxopt/_src/base.py
jaxopt/_src/bfgs.py
jaxopt/_src/bisection.py
jaxopt/_src/block_cd.py
jaxopt/_src/broyden.py
jaxopt/_src/cd_qp.py
jaxopt/_src/cond.py
jaxopt/_src/cvxpy_wrapper.py
jaxopt/_src/eq_qp.py
jaxopt/_src/fixed_point_iteration.py
jaxopt/_src/gauss_newton.py
jaxopt/_src/gradient_descent.py
jaxopt/_src/hager_zhang_linesearch.py
jaxopt/_src/implicit_diff.py
jaxopt/_src/isotonic.py
jaxopt/_src/iterative_refinement.py
jaxopt/_src/lbfgs.py
jaxopt/_src/lbfgsb.py
jaxopt/_src/levenberg_marquardt.py
jaxopt/_src/linear_operator.py
jaxopt/_src/linear_solve.py
jaxopt/_src/linesearch_util.py
jaxopt/_src/loop.py
jaxopt/_src/loss.py
jaxopt/_src/mirror_descent.py
jaxopt/_src/nonlinear_cg.py
jaxopt/_src/objective.py
jaxopt/_src/optax_wrapper.py
jaxopt/_src/osqp.py
jaxopt/_src/perturbations.py
jaxopt/_src/polyak_sgd.py
jaxopt/_src/projected_gradient.py
jaxopt/_src/projection.py
jaxopt/_src/prox.py
jaxopt/_src/proximal_gradient.py
jaxopt/_src/scipy_wrappers.py
jaxopt/_src/test_util.py
jaxopt/_src/tree_util.py
jaxopt/_src/zoom_linesearch.py
jaxopt-0.8.4.dist-info/licenses/LICENSE
jaxopt-0.8.4.dist-info/METADATA
jaxopt-0.8.4.dist-info/WHEEL
jaxopt-0.8.4.dist-info/top_level.txt
jaxopt-0.8.4.dist-info/RECORD
