Metadata-Version: 2.4
Name: jaxopt
Version: 0.8.4
Summary: Hardware accelerated, batchable and differentiable optimizers in JAX.
Home-page: https://github.com/google/jaxopt
Author: Google LLC
Author-email: no-reply@google.com
License: Apache 2.0
Keywords: optimization,root finding,implicit differentiation,jax
Classifier: Intended Audience :: Science/Research
Classifier: Topic :: Scientific/Engineering :: Artificial Intelligence
Classifier: License :: OSI Approved :: Apache Software License
Classifier: Programming Language :: Python :: 3
Classifier: Programming Language :: Python :: 3.9
Classifier: Programming Language :: Python :: 3.10
Classifier: Programming Language :: Python :: 3.11
License-File: LICENSE
Requires-Dist: jax>=0.2.18
Requires-Dist: jaxlib>=0.1.69
Requires-Dist: numpy>=1.18.4
Requires-Dist: scipy>=1.0.0
Dynamic: author
Dynamic: author-email
Dynamic: classifier
Dynamic: description
Dynamic: description-content-type
Dynamic: home-page
Dynamic: keywords
Dynamic: license
Dynamic: license-file
Dynamic: requires-dist
Dynamic: summary
